imdclient/IMDClient.py
imdclient/IMDProtocol.py
imdclient/__init__.py
imdclient/utils.py
imdclient/data/__init__.py
imdclient/data/gromacs/md/gromacs_struct.gro
imdclient/data/gromacs/md/gromacs_v3.top
imdclient/data/gromacs/md/gromacs_v3_nst1.mdp
imdclient/data/gromacs/md/gromacs_v3_nst8.mdp
imdclient/data/lammps/md/lammps_topol.data
imdclient/data/lammps/md/lammps_v3_nst_1.in
imdclient/data/lammps/md/lammps_v3_nst_8.in
imdclient/data/namd/md/alanin.params
imdclient/data/namd/md/alanin.pdb
imdclient/data/namd/md/alanin.psf
imdclient/data/namd/md/namd_v3_nst_1.namd
imdclient/data/namd/md/namd_v3_nst_8.namd
imdclient/tests/__init__.py
imdclient/tests/base.py
imdclient/tests/conftest.py
imdclient/tests/datafiles.py
imdclient/tests/minimalreader.py
imdclient/tests/server.py
imdclient/tests/test_gromacs.py
imdclient/tests/test_imdclient.py
imdclient/tests/test_lammps.py
imdclient/tests/test_namd.py
imdclient/tests/test_utils.py
imdclient/tests/utils.py
imdclient/tests/docker_testing/docker.md
imdclient-0.2.3.dist-info/licenses/AUTHORS.md
imdclient-0.2.3.dist-info/licenses/LICENSE
imdclient-0.2.3.dist-info/METADATA
imdclient-0.2.3.dist-info/WHEEL
imdclient-0.2.3.dist-info/top_level.txt
imdclient-0.2.3.dist-info/RECORD
