Metadata-Version: 2.4
Name: imdclient
Version: 0.2.3
Summary: Receiver for IMD v2 and v3 data from simulation engines like Gromacs, LAMMPS, and NAMD
Author-email: Lawson <ljwoods2@asu.edu>
Maintainer-email: Lawson <ljwoods2@asu.edu>, Amruthesh Thirumalaiswamy <athiru12@asu.edu>
License-Expression: MIT
Project-URL: source, https://github.com/becksteinlab/imdclient
Project-URL: documentation, https://imdclient.readthedocs.io
Keywords: molecular simulations
Requires-Python: >=3.10
License-File: LICENSE
License-File: AUTHORS.md
Requires-Dist: numpy
Provides-Extra: test
Requires-Dist: pytest>=6.0; extra == "test"
Requires-Dist: pytest-xdist>=2.5; extra == "test"
Requires-Dist: pytest-cov>=3.0; extra == "test"
Requires-Dist: MDAnalysis; extra == "test"
Requires-Dist: MDAnalysisTests; extra == "test"
Requires-Dist: docker-py; extra == "test"
Provides-Extra: doc
Requires-Dist: sphinx; extra == "doc"
Requires-Dist: mdanalysis-sphinx-theme>=1.0.1; extra == "doc"
Dynamic: license-file
